task1-chall/lfsr7.sv
module lfsr7 (
    input logic clk, // clock
    input logic rst, // reset
    input logic en, //enable
    output logic [7:1] data_out // pseudo—random output
);

logic [7:1] sreg;

always_ff @ (posedge clk, posedge rst)
    if (rst)
        sreg <= 7'b1;
    else
        sreg <= en ? {sreg[6:1], sreg[7] ^ sreg[3]} : sreg[6:1]; 

assign data_out = sreg;

endmodule

task1-chall/lfsr.vcd
$version Generated by VerilatedVcd $end
$date Tue Nov  7 20:38:22 2023 $end
$timescale 1ps $end

 $scope module TOP $end
  $var wire  1 # clk $end
  $var wire  7 & data_out [7:1] $end
  $var wire  1 % en $end
  $var wire  1 $ rst $end
  $scope module lfsr7 $end
   $var wire  1 # clk $end
   $var wire  7 & data_out [7:1] $end
   $var wire  1 % en $end
   $var wire  1 $ rst $end
   $var wire  7 ' sreg [7:1] $end
  $upscope $end
 $upscope $end
$enddefinitions $end


#0
1#
0$
1%
b0000000 &
b0000000 '
#1
0#
#2
1#
1$
0%
#3
0#
b0000001 &
b0000001 '
#4
1#
#5
0#
#6
1#
0$
#7
0#
#8
1#
#9
0#
#10
1#
#11
0#
#12
1#
#13
0#
#14
1#
#15
0#
#16
1#
#17
0#
#18
1#
#19
0#
#20
1#
#21
0#
#22
1#
#23
0#
#24
1#
#25
0#
#26
1#
#27
0#
#28
1#
#29
0#
#30
1#
#31
0#
#32
1#
#33
0#
#34
1#
#35
0#
#36
1#
#37
0#
#38
1#
#39
0#
#40
1#
#41
0#
#42
1#
#43
0#
#44
1#
#45
0#
#46
1#
#47
0#
#48
1#
#49
0#
#50
1#
#51
0#
#52
1#
#53
0#
#54
1#
#55
0#
#56
1#
#57
0#
#58
1#
#59
0#
#60
1#
#61
0#
#62
1#
#63
0#
#64
1#
#65
0#
#66
1#
#67
0#
#68
1#
#69
0#
#70
1#
1%
#71
0#
#72
1#
0%
b0000010 &
b0000010 '
#73
0#
#74
1#
#75
0#
#76
1#
#77
0#
#78
1#
#79
0#
#80
1#
#81
0#
#82
1#
#83
0#
#84
1#
#85
0#
#86
1#
#87
0#
#88
1#
#89
0#
#90
1#
1%
#91
0#
#92
1#
0%
b0000100 &
b0000100 '
#93
0#
#94
1#
#95
0#
#96
1#
#97
0#
#98
1#
1%
#99
0#
#100
1#
0%
b0001001 &
b0001001 '
#101
0#
#102
1#
1%
#103
0#
#104
1#
0%
b0010010 &
b0010010 '
#105
0#
#106
1#
1%
#107
0#
#108
1#
0%
b0100100 &
b0100100 '
#109
0#
#110
1#
1%
#111
0#
#112
1#
0%
b1001001 &
b1001001 '
#113
0#
#114
1#
1%
b0001001 &
b0001001 '
#115
0#
#116
1#
0%
b0010010 &
b0010010 '
#117
0#
#118
1#
1%
#119
0#
#120
1#
0%
b0100100 &
b0100100 '
#121
0#
#122
1#
1%
#123
0#
#124
1#
0%
b1001001 &
b1001001 '
#125
0#
#126
1#
1%
b0001001 &
b0001001 '
#127
0#
#128
1#
0%
b0010010 &
b0010010 '
